crunch_certificate/__init__.py
crunch_certificate/__main__.py
crunch_certificate/__version__.py
crunch_certificate/certificate.py
crunch_certificate/cli.py
crunch_certificate/pem.py
crunch_certificate/private_key.py
crunch_certificate/sign.py
crunch_certificate/web_sign.html
crunch_certificate-0.2.0.dist-info/METADATA
crunch_certificate-0.2.0.dist-info/WHEEL
crunch_certificate-0.2.0.dist-info/entry_points.txt
crunch_certificate-0.2.0.dist-info/top_level.txt
crunch_certificate-0.2.0.dist-info/RECORD
